multipart/__init__.py
multipart/_version.py
multipart/decoders.py
multipart/exceptions.py
multipart/multipart.py
multipart/tests/__init__.py
multipart/tests/compat.py
multipart/tests/test_multipart.py
python_multipart-0.0.4.dist-info/DESCRIPTION.rst
python_multipart-0.0.4.dist-info/METADATA
python_multipart-0.0.4.dist-info/RECORD
python_multipart-0.0.4.dist-info/WHEEL
python_multipart-0.0.4.dist-info/metadata.json
python_multipart-0.0.4.dist-info/top_level.txt
